README.txt
setup.cfg
setup.py
rfxcmd/__init__.py
rfxcmd/demo.py
rfxcmd/setup.py
rfxcmd/setup_basic.py
rfxcmd/setup_demo.py
rfxcmd.egg-info/PKG-INFO
rfxcmd.egg-info/SOURCES.txt
rfxcmd.egg-info/dependency_links.txt
rfxcmd.egg-info/entry_points.txt
rfxcmd.egg-info/requires.txt
rfxcmd.egg-info/top_level.txt